MANIFEST.in
README.md
README.rst
setup.py
fonty/__init__.py
fonty/fonty.py
fonty/setup.py
fonty/version.py
fonty.egg-info/PKG-INFO
fonty.egg-info/SOURCES.txt
fonty.egg-info/dependency_links.txt
fonty.egg-info/entry_points.txt
fonty.egg-info/requires.txt
fonty.egg-info/top_level.txt
fonty/commands/__init__.py
fonty/commands/install.py
fonty/commands/list.py
fonty/commands/source.py
fonty/commands/uninstall.py
fonty/commands/webfont.py
fonty/defaults/fonty.conf
fonty/defaults/sources.json
fonty/lib/__init__.py
fonty/lib/config.py
fonty/lib/constants.py
fonty/lib/font_name_ids.py
fonty/lib/json_encoder.py
fonty/lib/list_fonts.py
fonty/lib/progress.py
fonty/lib/search.py
fonty/lib/task.py
fonty/lib/telemetry.py
fonty/lib/terminal_size.py
fonty/lib/utils.py
fonty/lib/variants.py
fonty/lib/install/__init__.py
fonty/lib/install/install.py
fonty/lib/install/install_osx.py
fonty/lib/install/install_win32.py
fonty/lib/uninstall/__init__.py
fonty/lib/uninstall/uninstall.py
fonty/lib/uninstall/uninstall_osx.py
fonty/lib/uninstall/uninstall_win32.py
fonty/models/__init__.py
fonty/models/manifest.py
fonty/models/repository.py
fonty/models/subscription.py
fonty/models/font/__init__.py
fonty/models/font/family.py
fonty/models/font/font.py
fonty/models/font/font_format.py
fonty/models/font/installed_font.py
fonty/models/font/remote_font.py