Metadata-Version: 1.1
Name: fonty
Version: 0.2.6
Summary: fonty is a command line tool for installing, managing and converting fonts.
Home-page: https://github.com/jamesssooi/fonty
Author: James Ooi
Author-email: wengteikooi@gmail.com
License: Apache License 2.0
Keywords: font fonts typeface cli tool install uninstall convert manage
Platform: UNKNOWN
Classifier: Development Status :: 3 - Alpha
Classifier: Environment :: Console
Classifier: License :: OSI Approved :: Apache Software License
Classifier: Intended Audience :: Developers
Classifier: Intended Audience :: End Users/Desktop
Classifier: Intended Audience :: System Administrators
Classifier: Operating System :: MacOS
Classifier: Operating System :: Microsoft :: Windows
Classifier: Programming Language :: Python :: 3 :: Only
Classifier: Topic :: Multimedia :: Graphics
Classifier: Topic :: Terminals
Classifier: Topic :: Utilities
